crawlMp/__init__.py
crawlMp/constants.py
crawlMp/crawlMp.py
crawlMp/crawlWorker.py
crawlMp/enums.py
crawlMp/results.py
crawlMp/actions/__init__.py
crawlMp/actions/action.py
crawlMp/actions/action_fs.py
crawlMp/crawlers/__init__.py
crawlMp/crawlers/crawler.py
crawlMp/crawlers/crawler_fs.py
crawlMp/scripts/__init__.py
crawlMp/snippets/__init__.py
crawlMp/snippets/mixins.py
crawlMp/snippets/output.py
crawlMp/tests/__init__.py
crawlMp/tests/conftest.py
crawlMp/tests/fs_files.txt
crawlMp/tests/fs_win_files.txt
crawlMp/tests/test_crawlMp.py
crawlMp/tests/test_crawlWorker.py
crawlMp/tests/test_fileCrawler.py
crawlMp/tests/test_fs_actions.py
crawlMp/tests/test_snippets.py
crawlMp-0.3.7.data/scripts/search_fs_mp
crawlMp-0.3.7.dist-info/LICENSE
crawlMp-0.3.7.dist-info/METADATA
crawlMp-0.3.7.dist-info/WHEEL
crawlMp-0.3.7.dist-info/top_level.txt
crawlMp-0.3.7.dist-info/RECORD
