Metadata-Version: 2.1
Name: crawlMp
Version: 0.3.7
Summary: Multiprocess Crawler
Home-page: https://github.com/domarm-comat/crawlMp
Author: Martin Domaracký
Author-email: domarm@comat.sk
License: MIT
Platform: UNKNOWN
Classifier: Programming Language :: Python :: 3
Classifier: Operating System :: OS Independent
Classifier: Topic :: Software Development :: Libraries
Classifier: License :: OSI Approved :: MIT License
Classifier: Natural Language :: English
Classifier: Intended Audience :: Science/Research
Requires-Python: >=3.6
License-File: LICENSE
Requires-Dist: coverage (>=6.2)
Requires-Dist: pyfakefs (>=4.5.3)
Requires-Dist: pytest (>=6.2.5)
Requires-Dist: pandas (>=1.1.5)
